{
    "isSuccess": true,
    "httpCode": 200,
    "data": [
        {
            "staffName": "Mostafa",
            "staffNameAr": "مصطفsssssى رأفت",
            "staffId": 15,
            "inTime1": "08:32 AM",
            "outTime1": null,
            "isTwoTimeShifting": false,
            "inTime2": null,
            "outTime2": null,
            "isOnTimeAttendanceShift1": false,
            "isLateAttendanceShift1": true,
            "isEarlyOutShift1": false,
            "isAbsenceShift1": false,
            "isOnTimeAttendanceShift2": false,
            "isLateAttendanceShift2": false,
            "isEarlyOutShift2": false,
            "isAbsenceShift2": false,
            "notes": []
        },
        {
            "staffName": "Waleed",
            "staffNameAr": "غياب الصباح وليد",
            "staffId": 17,
            "inTime1": null,
            "outTime1": "08:14 PM",
            "isTwoTimeShifting": false,
            "inTime2": null,
            "outTime2": null,
            "isOnTimeAttendanceShift1": false,
            "isLateAttendanceShift1": false,
            "isEarlyOutShift1": false,
            "isAbsenceShift1": true,
            "isOnTimeAttendanceShift2": false,
            "isLateAttendanceShift2": false,
            "isEarlyOutShift2": false,
            "isAbsenceShift2": false,
            "notes": []
        },
        {
            "staffName": "Waleed",
            "staffNameAr": "غياب المساء وليد",
            "staffId": 17,
            "inTime1": "08:14 AM",
            "outTime1": null,
            "isTwoTimeShifting": false,
            "inTime2": null,
            "outTime2": null,
            "isOnTimeAttendanceShift1": true,
            "isLateAttendanceShift1": false,
            "isEarlyOutShift1": false,
            "isAbsenceShift1": true,
            "isOnTimeAttendanceShift2": false,
            "isLateAttendanceShift2": false,
            "isEarlyOutShift2": false,
            "isAbsenceShift2": false,
            "notes": []
        },
        {
            "staffName": "Waleed",
            "staffNameAr": "غياب ومتاخر المساء وليد",
            "staffId": 17,
            "inTime1": "08:14 AM",
            "outTime1": null,
            "isTwoTimeShifting": false,
            "inTime2": null,
            "outTime2": null,
            "isOnTimeAttendanceShift1": true,
            "isLateAttendanceShift1": true,
            "isEarlyOutShift1": false,
            "isAbsenceShift1": true,
            "isOnTimeAttendanceShift2": false,
            "isLateAttendanceShift2": false,
            "isEarlyOutShift2": false,
            "isAbsenceShift2": false,
            "notes": []
        },
        {
            "staffName": "Mahmood",
            "staffNameAr": "محمود سعد",
            "staffId": 18,
            "inTime1": null,
            "outTime1": null,
            "isTwoTimeShifting": false,
            "inTime2": null,
            "outTime2": null,
            "isOnTimeAttendanceShift1": false,
            "isLateAttendanceShift1": false,
            "isEarlyOutShift1": false,
            "isAbsenceShift1": true,
            "isOnTimeAttendanceShift2": false,
            "isLateAttendanceShift2": false,
            "isEarlyOutShift2": false,
            "isAbsenceShift2": false,
            "notes": []
        },
        {
            "staffName": "Rushdi",
            "staffNameAr": "رشدي إسكندر",
            "staffId": 19,
            "inTime1": null,
            "outTime1": null,
            "isTwoTimeShifting": false,
            "inTime2": null,
            "outTime2": null,
            "isOnTimeAttendanceShift1": false,
            "isLateAttendanceShift1": false,
            "isEarlyOutShift1": false,
            "isAbsenceShift1": true,
            "isOnTimeAttendanceShift2": false,
            "isLateAttendanceShift2": false,
            "isEarlyOutShift2": false,
            "isAbsenceShift2": false,
            "notes": []
        },
        {
            "staffName": "Maher Ali",
            "staffNameAr": "ماهر علي",
            "staffId": 20,
            "inTime1": "08:22 AM",
            "outTime1": null,
            "isTwoTimeShifting": false,
            "inTime2": null,
            "outTime2": null,
            "isOnTimeAttendanceShift1": false,
            "isLateAttendanceShift1": true,
            "isEarlyOutShift1": false,
            "isAbsenceShift1": false,
            "isOnTimeAttendanceShift2": false,
            "isLateAttendanceShift2": false,
            "isEarlyOutShift2": false,
            "isAbsenceShift2": false,
            "notes": []
        },
        {
            "staffName": "Mohammed Yaqoob",
            "staffNameAr": "محمد يعقوب",
            "staffId": 22,
            "inTime1": "07:53 AM",
            "outTime1": null,
            "isTwoTimeShifting": false,
            "inTime2": null,
            "outTime2": null,
            "isOnTimeAttendanceShift1": true,
            "isLateAttendanceShift1": false,
            "isEarlyOutShift1": false,
            "isAbsenceShift1": false,
            "isOnTimeAttendanceShift2": false,
            "isLateAttendanceShift2": false,
            "isEarlyOutShift2": false,
            "isAbsenceShift2": false,
            "notes": []
        },
        {
            "staffName": "Mohamed Ghazy",
            "staffNameAr": "محمد غازي",
            "staffId": 23,
            "inTime1": null,
            "outTime1": null,
            "isTwoTimeShifting": false,
            "inTime2": null,
            "outTime2": null,
            "isOnTimeAttendanceShift1": false,
            "isLateAttendanceShift1": false,
            "isEarlyOutShift1": false,
            "isAbsenceShift1": true,
            "isOnTimeAttendanceShift2": false,
            "isLateAttendanceShift2": false,
            "isEarlyOutShift2": false,
            "isAbsenceShift2": false,
            "notes": []
        },
        {
            "staffName": "Mohammed Fadil",
            "staffNameAr": "محمد ابو الفضل",
            "staffId": 24,
            "inTime1": "08:04 AM",
            "outTime1": null,
            "isTwoTimeShifting": false,
            "inTime2": null,
            "outTime2": null,
            "isOnTimeAttendanceShift1": true,
            "isLateAttendanceShift1": false,
            "isEarlyOutShift1": false,
            "isAbsenceShift1": false,
            "isOnTimeAttendanceShift2": false,
            "isLateAttendanceShift2": false,
            "isEarlyOutShift2": false,
            "isAbsenceShift2": false,
            "notes": []
        },
        {
            "staffName": "Ammar",
            "staffNameAr": "عمار",
            "staffId": 25,
            "inTime1": null,
            "outTime1": null,
            "isTwoTimeShifting": false,
            "inTime2": null,
            "outTime2": null,
            "isOnTimeAttendanceShift1": false,
            "isLateAttendanceShift1": false,
            "isEarlyOutShift1": false,
            "isAbsenceShift1": true,
            "isOnTimeAttendanceShift2": false,
            "isLateAttendanceShift2": false,
            "isEarlyOutShift2": false,
            "isAbsenceShift2": false,
            "notes": []
        },
        {
            "staffName": "Adualah Hasan",
            "staffNameAr": "عبدالله حسن",
            "staffId": 26,
            "inTime1": "08:09 AM",
            "outTime1": null,
            "isTwoTimeShifting": false,
            "inTime2": null,
            "outTime2": null,
            "isOnTimeAttendanceShift1": true,
            "isLateAttendanceShift1": false,
            "isEarlyOutShift1": false,
            "isAbsenceShift1": false,
            "isOnTimeAttendanceShift2": false,
            "isLateAttendanceShift2": false,
            "isEarlyOutShift2": false,
            "isAbsenceShift2": false,
            "notes": []
        },
        {
            "staffName": "Islam",
            "staffNameAr": "اسلام",
            "staffId": 27,
            "inTime1": "08:27 AM",
            "outTime1": null,
            "isTwoTimeShifting": false,
            "inTime2": null,
            "outTime2": null,
            "isOnTimeAttendanceShift1": false,
            "isLateAttendanceShift1": true,
            "isEarlyOutShift1": false,
            "isAbsenceShift1": false,
            "isOnTimeAttendanceShift2": false,
            "isLateAttendanceShift2": false,
            "isEarlyOutShift2": false,
            "isAbsenceShift2": false,
            "notes": []
        },
        {
            "staffName": "hasan",
            "staffNameAr": "حسن",
            "staffId": 28,
            "inTime1": "08:16 AM",
            "outTime1": null,
            "isTwoTimeShifting": false,
            "inTime2": null,
            "outTime2": null,
            "isOnTimeAttendanceShift1": false,
            "isLateAttendanceShift1": true,
            "isEarlyOutShift1": false,
            "isAbsenceShift1": false,
            "isOnTimeAttendanceShift2": false,
            "isLateAttendanceShift2": false,
            "isEarlyOutShift2": false,
            "isAbsenceShift2": false,
            "notes": []
        },
        {
            "staffName": "amro",
            "staffNameAr": "عمرو",
            "staffId": 29,
            "inTime1": "08:21 AM",
            "outTime1": null,
            "isTwoTimeShifting": false,
            "inTime2": null,
            "outTime2": null,
            "isOnTimeAttendanceShift1": false,
            "isLateAttendanceShift1": true,
            "isEarlyOutShift1": false,
            "isAbsenceShift1": false,
            "isOnTimeAttendanceShift2": false,
            "isLateAttendanceShift2": false,
            "isEarlyOutShift2": false,
            "isAbsenceShift2": false,
            "notes": []
        },
        {
            "staffName": "husain",
            "staffNameAr": "حسين شعبان",
            "staffId": 30,
            "inTime1": "08:11 AM",
            "outTime1": null,
            "isTwoTimeShifting": false,
            "inTime2": null,
            "outTime2": null,
            "isOnTimeAttendanceShift1": true,
            "isLateAttendanceShift1": false,
            "isEarlyOutShift1": false,
            "isAbsenceShift1": false,
            "isOnTimeAttendanceShift2": false,
            "isLateAttendanceShift2": false,
            "isEarlyOutShift2": false,
            "isAbsenceShift2": false,
            "notes": []
        },
        {
            "staffName": "mark",
            "staffNameAr": "مارك",
            "staffId": 31,
            "inTime1": null,
            "outTime1": null,
            "isTwoTimeShifting": false,
            "inTime2": null,
            "outTime2": null,
            "isOnTimeAttendanceShift1": false,
            "isLateAttendanceShift1": false,
            "isEarlyOutShift1": false,
            "isAbsenceShift1": true,
            "isOnTimeAttendanceShift2": false,
            "isLateAttendanceShift2": false,
            "isEarlyOutShift2": false,
            "isAbsenceShift2": false,
            "notes": []
        },
        {
            "staffName": "kamal",
            "staffNameAr": "كمال",
            "staffId": 32,
            "inTime1": "08:27 AM",
            "outTime1": null,
            "isTwoTimeShifting": false,
            "inTime2": null,
            "outTime2": null,
            "isOnTimeAttendanceShift1": false,
            "isLateAttendanceShift1": true,
            "isEarlyOutShift1": false,
            "isAbsenceShift1": false,
            "isOnTimeAttendanceShift2": false,
            "isLateAttendanceShift2": false,
            "isEarlyOutShift2": false,
            "isAbsenceShift2": false,
            "notes": []
        },
        {
            "staffName": "lio",
            "staffNameAr": "ليو",
            "staffId": 33,
            "inTime1": null,
            "outTime1": null,
            "isTwoTimeShifting": false,
            "inTime2": null,
            "outTime2": null,
            "isOnTimeAttendanceShift1": false,
            "isLateAttendanceShift1": false,
            "isEarlyOutShift1": false,
            "isAbsenceShift1": true,
            "isOnTimeAttendanceShift2": false,
            "isLateAttendanceShift2": false,
            "isEarlyOutShift2": false,
            "isAbsenceShift2": false,
            "notes": []
        },
        {
            "staffName": "eirc",
            "staffNameAr": "ايريك",
            "staffId": 34,
            "inTime1": null,
            "outTime1": null,
            "isTwoTimeShifting": false,
            "inTime2": null,
            "outTime2": null,
            "isOnTimeAttendanceShift1": false,
            "isLateAttendanceShift1": false,
            "isEarlyOutShift1": false,
            "isAbsenceShift1": true,
            "isOnTimeAttendanceShift2": false,
            "isLateAttendanceShift2": false,
            "isEarlyOutShift2": false,
            "isAbsenceShift2": false,
            "notes": []
        },
        {
            "staffName": "herbit",
            "staffNameAr": "هربرت",
            "staffId": 35,
            "inTime1": null,
            "outTime1": null,
            "isTwoTimeShifting": false,
            "inTime2": null,
            "outTime2": null,
            "isOnTimeAttendanceShift1": false,
            "isLateAttendanceShift1": false,
            "isEarlyOutShift1": false,
            "isAbsenceShift1": true,
            "isOnTimeAttendanceShift2": false,
            "isLateAttendanceShift2": false,
            "isEarlyOutShift2": false,
            "isAbsenceShift2": false,
            "notes": []
        },
        {
            "staffName": "julie",
            "staffNameAr": "جولي",
            "staffId": 36,
            "inTime1": null,
            "outTime1": null,
            "isTwoTimeShifting": false,
            "inTime2": null,
            "outTime2": null,
            "isOnTimeAttendanceShift1": false,
            "isLateAttendanceShift1": false,
            "isEarlyOutShift1": false,
            "isAbsenceShift1": true,
            "isOnTimeAttendanceShift2": false,
            "isLateAttendanceShift2": false,
            "isEarlyOutShift2": false,
            "isAbsenceShift2": false,
            "notes": []
        },
        {
            "staffName": "Rolly",
            "staffNameAr": "رولي في كاستر",
            "staffId": 39,
            "inTime1": "08:21 AM",
            "outTime1": null,
            "isTwoTimeShifting": false,
            "inTime2": null,
            "outTime2": null,
            "isOnTimeAttendanceShift1": false,
            "isLateAttendanceShift1": true,
            "isEarlyOutShift1": false,
            "isAbsenceShift1": false,
            "isOnTimeAttendanceShift2": false,
            "isLateAttendanceShift2": false,
            "isEarlyOutShift2": false,
            "isAbsenceShift2": false,
            "notes": []
        },
        {
            "staffName": "mohamed ameer",
            "staffNameAr": "محمد عامر",
            "staffId": 40,
            "inTime1": null,
            "outTime1": null,
            "isTwoTimeShifting": false,
            "inTime2": null,
            "outTime2": null,
            "isOnTimeAttendanceShift1": false,
            "isLateAttendanceShift1": false,
            "isEarlyOutShift1": false,
            "isAbsenceShift1": true,
            "isOnTimeAttendanceShift2": false,
            "isLateAttendanceShift2": false,
            "isEarlyOutShift2": false,
            "isAbsenceShift2": false,
            "notes": []
        },
        {
            "staffName": "rawan gamal",
            "staffNameAr": "روان جمال",
            "staffId": 41,
            "inTime1": "08:00 AM",
            "outTime1": null,
            "isTwoTimeShifting": false,
            "inTime2": null,
            "outTime2": null,
            "isOnTimeAttendanceShift1": true,
            "isLateAttendanceShift1": false,
            "isEarlyOutShift1": false,
            "isAbsenceShift1": false,
            "isOnTimeAttendanceShift2": false,
            "isLateAttendanceShift2": false,
            "isEarlyOutShift2": false,
            "isAbsenceShift2": false,
            "notes": []
        },
        {
            "staffName": "Maryam Alshahari",
            "staffNameAr": "مريم احمد الشهاري",
            "staffId": 42,
            "inTime1": "08:23 AM",
            "outTime1": null,
            "isTwoTimeShifting": false,
            "inTime2": null,
            "outTime2": null,
            "isOnTimeAttendanceShift1": false,
            "isLateAttendanceShift1": true,
            "isEarlyOutShift1": false,
            "isAbsenceShift1": false,
            "isOnTimeAttendanceShift2": false,
            "isLateAttendanceShift2": false,
            "isEarlyOutShift2": false,
            "isAbsenceShift2": false,
            "notes": []
        },
        {
            "staffName": "abd alslam abo alkshem",
            "staffNameAr": "عبدالسلام ابو الكاشيم",
            "staffId": 45,
            "inTime1": "07:47 AM",
            "outTime1": null,
            "isTwoTimeShifting": false,
            "inTime2": null,
            "outTime2": null,
            "isOnTimeAttendanceShift1": true,
            "isLateAttendanceShift1": false,
            "isEarlyOutShift1": false,
            "isAbsenceShift1": false,
            "isOnTimeAttendanceShift2": false,
            "isLateAttendanceShift2": false,
            "isEarlyOutShift2": false,
            "isAbsenceShift2": false,
            "notes": []
        },
        {
            "staffName": "hamod altawil",
            "staffNameAr": "حمود قايد الطويل",
            "staffId": 46,
            "inTime1": null,
            "outTime1": null,
            "isTwoTimeShifting": false,
            "inTime2": null,
            "outTime2": null,
            "isOnTimeAttendanceShift1": false,
            "isLateAttendanceShift1": false,
            "isEarlyOutShift1": false,
            "isAbsenceShift1": true,
            "isOnTimeAttendanceShift2": false,
            "isLateAttendanceShift2": false,
            "isEarlyOutShift2": false,
            "isAbsenceShift2": false,
            "notes": []
        },
        {
            "staffName": "Noel Jhun",
            "staffNameAr": "نو ويل",
            "staffId": 47,
            "inTime1": "08:21 AM",
            "outTime1": null,
            "isTwoTimeShifting": false,
            "inTime2": null,
            "outTime2": null,
            "isOnTimeAttendanceShift1": false,
            "isLateAttendanceShift1": true,
            "isEarlyOutShift1": false,
            "isAbsenceShift1": false,
            "isOnTimeAttendanceShift2": false,
            "isLateAttendanceShift2": false,
            "isEarlyOutShift2": false,
            "isAbsenceShift2": false,
            "notes": []
        },
        {
            "staffName": "ABDELFATAH SHABAN MUSA GUBARA",
            "staffNameAr": "عبدالفتاح شعبان موسي جبارة",
            "staffId": 48,
            "inTime1": "09:01 AM",
            "outTime1": null,
            "isTwoTimeShifting": true,
            "inTime2": null,
            "outTime2": null,
            "isOnTimeAttendanceShift1": false,
            "isLateAttendanceShift1": true,
            "isEarlyOutShift1": false,
            "isAbsenceShift1": false,
            "isOnTimeAttendanceShift2": false,
            "isLateAttendanceShift2": false,
            "isEarlyOutShift2": false,
            "isAbsenceShift2": false,
            "notes": []
        },
        {
            "staffName": "ahmed saliman",
            "staffNameAr": "احمد سليمان حمدي",
            "staffId": 50,
            "inTime1": null,
            "outTime1": null,
            "isTwoTimeShifting": false,
            "inTime2": null,
            "outTime2": null,
            "isOnTimeAttendanceShift1": false,
            "isLateAttendanceShift1": false,
            "isEarlyOutShift1": false,
            "isAbsenceShift1": false,
            "isOnTimeAttendanceShift2": false,
            "isLateAttendanceShift2": false,
            "isEarlyOutShift2": false,
            "isAbsenceShift2": false,
            "notes": []
        },
        {
            "staffName": "adel abdo",
            "staffNameAr": "عادل عبده موسي سويدي",
            "staffId": 51,
            "inTime1": null,
            "outTime1": null,
            "isTwoTimeShifting": false,
            "inTime2": null,
            "outTime2": null,
            "isOnTimeAttendanceShift1": false,
            "isLateAttendanceShift1": false,
            "isEarlyOutShift1": false,
            "isAbsenceShift1": false,
            "isOnTimeAttendanceShift2": false,
            "isLateAttendanceShift2": false,
            "isEarlyOutShift2": false,
            "isAbsenceShift2": false,
            "notes": []
        },
        {
            "staffName": "AMJAD HOSAIN",
            "staffNameAr": "أمجد حسين",
            "staffId": 52,
            "inTime1": null,
            "outTime1": null,
            "isTwoTimeShifting": true,
            "inTime2": null,
            "outTime2": null,
            "isOnTimeAttendanceShift1": false,
            "isLateAttendanceShift1": false,
            "isEarlyOutShift1": false,
            "isAbsenceShift1": true,
            "isOnTimeAttendanceShift2": false,
            "isLateAttendanceShift2": false,
            "isEarlyOutShift2": false,
            "isAbsenceShift2": false,
            "notes": []
        },
        {
            "staffName": "SANWAR HOSSAIN HARUNORRASHID",
            "staffNameAr": "هارون الرشيد حسين سنوار",
            "staffId": 53,
            "inTime1": "08:46 AM",
            "outTime1": null,
            "isTwoTimeShifting": true,
            "inTime2": null,
            "outTime2": null,
            "isOnTimeAttendanceShift1": true,
            "isLateAttendanceShift1": false,
            "isEarlyOutShift1": false,
            "isAbsenceShift1": false,
            "isOnTimeAttendanceShift2": false,
            "isLateAttendanceShift2": false,
            "isEarlyOutShift2": false,
            "isAbsenceShift2": false,
            "notes": []
        },
        {
            "staffName": "BIEN CHESTER CABUYAO",
            "staffNameAr": "بن شيستر",
            "staffId": 57,
            "inTime1": null,
            "outTime1": null,
            "isTwoTimeShifting": true,
            "inTime2": null,
            "outTime2": null,
            "isOnTimeAttendanceShift1": false,
            "isLateAttendanceShift1": false,
            "isEarlyOutShift1": false,
            "isAbsenceShift1": true,
            "isOnTimeAttendanceShift2": false,
            "isLateAttendanceShift2": false,
            "isEarlyOutShift2": false,
            "isAbsenceShift2": false,
            "notes": []
        },
        {
            "staffName": "hussenalhakamy",
            "staffNameAr": "حسين يحي علي حكمي",
            "staffId": 58,
            "inTime1": null,
            "outTime1": null,
            "isTwoTimeShifting": false,
            "inTime2": null,
            "outTime2": null,
            "isOnTimeAttendanceShift1": false,
            "isLateAttendanceShift1": false,
            "isEarlyOutShift1": false,
            "isAbsenceShift1": false,
            "isOnTimeAttendanceShift2": false,
            "isLateAttendanceShift2": false,
            "isEarlyOutShift2": false,
            "isAbsenceShift2": false,
            "notes": []
        },
        {
            "staffName": "ezaldy",
            "staffNameAr": "عزالدين محمد سرور",
            "staffId": 59,
            "inTime1": "08:47 AM",
            "outTime1": null,
            "isTwoTimeShifting": true,
            "inTime2": null,
            "outTime2": null,
            "isOnTimeAttendanceShift1": true,
            "isLateAttendanceShift1": false,
            "isEarlyOutShift1": false,
            "isAbsenceShift1": false,
            "isOnTimeAttendanceShift2": false,
            "isLateAttendanceShift2": false,
            "isEarlyOutShift2": false,
            "isAbsenceShift2": false,
            "notes": []
        },
        {
            "staffName": "anas",
            "staffNameAr": "انس",
            "staffId": 61,
            "inTime1": "08:29 AM",
            "outTime1": null,
            "isTwoTimeShifting": false,
            "inTime2": null,
            "outTime2": null,
            "isOnTimeAttendanceShift1": false,
            "isLateAttendanceShift1": true,
            "isEarlyOutShift1": false,
            "isAbsenceShift1": false,
            "isOnTimeAttendanceShift2": false,
            "isLateAttendanceShift2": false,
            "isEarlyOutShift2": false,
            "isAbsenceShift2": false,
            "notes": []
        },
        {
            "staffName": "salem ahmed",
            "staffNameAr": "سالم احمد",
            "staffId": 62,
            "inTime1": "07:23 AM",
            "outTime1": null,
            "isTwoTimeShifting": false,
            "inTime2": null,
            "outTime2": null,
            "isOnTimeAttendanceShift1": true,
            "isLateAttendanceShift1": false,
            "isEarlyOutShift1": false,
            "isAbsenceShift1": false,
            "isOnTimeAttendanceShift2": false,
            "isLateAttendanceShift2": false,
            "isEarlyOutShift2": false,
            "isAbsenceShift2": false,
            "notes": []
        },
        {
            "staffName": "naif",
            "staffNameAr": "نايف موسي ابراهيم خال",
            "staffId": 63,
            "inTime1": null,
            "outTime1": null,
            "isTwoTimeShifting": false,
            "inTime2": null,
            "outTime2": null,
            "isOnTimeAttendanceShift1": false,
            "isLateAttendanceShift1": false,
            "isEarlyOutShift1": false,
            "isAbsenceShift1": false,
            "isOnTimeAttendanceShift2": false,
            "isLateAttendanceShift2": false,
            "isEarlyOutShift2": false,
            "isAbsenceShift2": false,
            "notes": []
        },
        {
            "staffName": "RICKY",
            "staffNameAr": "ريكى كانا",
            "staffId": 73,
            "inTime1": null,
            "outTime1": null,
            "isTwoTimeShifting": false,
            "inTime2": null,
            "outTime2": null,
            "isOnTimeAttendanceShift1": false,
            "isLateAttendanceShift1": false,
            "isEarlyOutShift1": false,
            "isAbsenceShift1": true,
            "isOnTimeAttendanceShift2": false,
            "isLateAttendanceShift2": false,
            "isEarlyOutShift2": false,
            "isAbsenceShift2": false,
            "notes": []
        },
        {
            "staffName": "ahmed hassan",
            "staffNameAr": "أحمد حسان",
            "staffId": 75,
            "inTime1": "08:26 AM",
            "outTime1": null,
            "isTwoTimeShifting": false,
            "inTime2": null,
            "outTime2": null,
            "isOnTimeAttendanceShift1": false,
            "isLateAttendanceShift1": true,
            "isEarlyOutShift1": false,
            "isAbsenceShift1": false,
            "isOnTimeAttendanceShift2": false,
            "isLateAttendanceShift2": false,
            "isEarlyOutShift2": false,
            "isAbsenceShift2": false,
            "notes": []
        },
        {
            "staffName": "ameen mohammed",
            "staffNameAr": "ابو عبيده امين محمد",
            "staffId": 80,
            "inTime1": "08:46 AM",
            "outTime1": null,
            "isTwoTimeShifting": true,
            "inTime2": null,
            "outTime2": null,
            "isOnTimeAttendanceShift1": true,
            "isLateAttendanceShift1": false,
            "isEarlyOutShift1": false,
            "isAbsenceShift1": false,
            "isOnTimeAttendanceShift2": false,
            "isLateAttendanceShift2": false,
            "isEarlyOutShift2": false,
            "isAbsenceShift2": false,
            "notes": []
        },
        {
            "staffName": "Carlos",
            "staffNameAr": "كارلوس",
            "staffId": 81,
            "inTime1": "08:46 AM",
            "outTime1": null,
            "isTwoTimeShifting": true,
            "inTime2": null,
            "outTime2": null,
            "isOnTimeAttendanceShift1": true,
            "isLateAttendanceShift1": false,
            "isEarlyOutShift1": false,
            "isAbsenceShift1": false,
            "isOnTimeAttendanceShift2": false,
            "isLateAttendanceShift2": false,
            "isEarlyOutShift2": false,
            "isAbsenceShift2": false,
            "notes": []
        },
        {
            "staffName": "abdulaziz abdalah",
            "staffNameAr": "عبدالعزيز عبدالله ناصر",
            "staffId": 82,
            "inTime1": "08:14 AM",
            "outTime1": null,
            "isTwoTimeShifting": false,
            "inTime2": null,
            "outTime2": null,
            "isOnTimeAttendanceShift1": true,
            "isLateAttendanceShift1": false,
            "isEarlyOutShift1": false,
            "isAbsenceShift1": false,
            "isOnTimeAttendanceShift2": false,
            "isLateAttendanceShift2": false,
            "isEarlyOutShift2": false,
            "isAbsenceShift2": false,
            "notes": []
        },
        {
            "staffName": "mohammed mahmuod",
            "staffNameAr": "محمد محمود صادق",
            "staffId": 83,
            "inTime1": "07:58 AM",
            "outTime1": null,
            "isTwoTimeShifting": false,
            "inTime2": null,
            "outTime2": null,
            "isOnTimeAttendanceShift1": true,
            "isLateAttendanceShift1": false,
            "isEarlyOutShift1": false,
            "isAbsenceShift1": false,
            "isOnTimeAttendanceShift2": false,
            "isLateAttendanceShift2": false,
            "isEarlyOutShift2": false,
            "isAbsenceShift2": false,
            "notes": []
        },
        {
            "staffName": "bassam abdu",
            "staffNameAr": "بسام عبدالباسط",
            "staffId": 84,
            "inTime1": "08:13 AM",
            "outTime1": "05:15",
            "isTwoTimeShifting": false,
            "inTime2": null,
            "outTime2": null,
            "isOnTimeAttendanceShift1": true,
            "isLateAttendanceShift1": false,
            "isEarlyOutShift1": false,
            "isAbsenceShift1": false,
            "isOnTimeAttendanceShift2": false,
            "isLateAttendanceShift2": false,
            "isEarlyOutShift2": false,
            "isAbsenceShift2": false,
            "notes": []
        },
        {
            "staffName": "abdulbagi elemam abdulwahab ",
            "staffNameAr": "عبدالباقى الامام عبدالوهاب",
            "staffId": 85,
            "inTime1": "07:58 AM",
            "outTime1": null,
            "isTwoTimeShifting": false,
            "inTime2": null,
            "outTime2": null,
            "isOnTimeAttendanceShift1": true,
            "isLateAttendanceShift1": false,
            "isEarlyOutShift1": false,
            "isAbsenceShift1": false,
            "isOnTimeAttendanceShift2": false,
            "isLateAttendanceShift2": false,
            "isEarlyOutShift2": false,
            "isAbsenceShift2": false,
            "notes": []
        }
    ],
    "errorList": []
}
